{"mappings": [{"item": {"url": "", "title": "Optimal Living Systems \u2014 Documentation"}, "tags": ["Onboarding", "internal"]}, {"item": {"url": "guides/", "title": "Guides"}, "tags": ["How-To", "internal"]}, {"item": {"url": "guides/contributing/", "title": "Contributing"}, "tags": ["How-To", "Process"]}, {"item": {"url": "guides/onboarding/", "title": "Onboarding"}, "tags": ["Onboarding", "internal"]}, {"item": {"url": "infrastructure/", "title": "Infrastructure"}, "tags": ["Infrastructure", "internal"]}, {"item": {"url": "infrastructure/dev-setup/", "title": "Development Setup"}, "tags": ["Infrastructure", "Tutorial"]}, {"item": {"url": "infrastructure/tools/", "title": "Tools & Platforms"}, "tags": ["Infrastructure", "Reference"]}, {"item": {"url": "infrastructure/reference/", "title": "Infrastructure Reference"}, "tags": ["Infrastructure", "Reference"]}, {"item": {"url": "operations/decisions/", "title": "Decisions"}, "tags": ["Infrastructure", "Process"]}, {"item": {"url": "organization/", "title": "Organization"}, "tags": ["Strategy", "internal"]}, {"item": {"url": "organization/governance/", "title": "Governance"}, "tags": ["Process", "internal"]}, {"item": {"url": "organization/mission/", "title": "Mission & Values"}, "tags": ["Strategy", "internal"]}, {"item": {"url": "organization/policies/", "title": "Policies"}, "tags": ["Process", "internal"]}, {"item": {"url": "projects/", "title": "Projects"}, "tags": ["Strategy", "internal"]}, {"item": {"url": "projects/ai-lab/", "title": "AI Lab"}, "tags": ["AI Lab", "internal"]}, {"item": {"url": "projects/ai-lab/overview/", "title": "Overview"}, "tags": ["AI Lab", "Reference"]}, {"item": {"url": "projects/ai-lab/guides/", "title": "AI Lab Guides"}, "tags": ["AI Lab", "How-To"]}, {"item": {"url": "projects/ai-lab/guides/onboarding/", "title": "AI Lab Onboarding"}, "tags": ["AI Lab", "Onboarding"]}, {"item": {"url": "projects/ai-lab/public/", "title": "AI Lab \u2014 Public"}, "tags": ["AI Lab", "external"]}, {"item": {"url": "projects/ai-lab/public/about/", "title": "About the AI Lab"}, "tags": ["AI Lab", "external"]}, {"item": {"url": "projects/ai-lab/public/how-to-engage/", "title": "Collaborate with AI Lab"}, "tags": ["AI Lab", "external"]}, {"item": {"url": "projects/ai-lab/public/methodology/", "title": "AI Lab Methodology"}, "tags": ["AI Lab", "external"]}, {"item": {"url": "projects/ai-lab/reference/", "title": "AI Lab Reference"}, "tags": ["AI Lab", "Reference"]}, {"item": {"url": "projects/ai-lab/roles/", "title": "AI Lab Roles"}, "tags": ["AI Lab", "ML Engineer"]}, {"item": {"url": "projects/ai-lab/teams/", "title": "AI Lab Teams"}, "tags": ["AI Lab", "internal"]}, {"item": {"url": "projects/ai-lab/workflows/", "title": "AI Lab Workflows"}, "tags": ["AI Lab", "Pipeline"]}, {"item": {"url": "projects/research-lab/", "title": "Research Lab"}, "tags": ["Research Lab", "internal"]}, {"item": {"url": "projects/research-lab/overview/", "title": "Overview"}, "tags": ["Reference", "Research Lab"]}, {"item": {"url": "projects/research-lab/guides/", "title": "Research Lab Guides"}, "tags": ["How-To", "Research Lab"]}, {"item": {"url": "projects/research-lab/guides/onboarding/", "title": "Research Lab Onboarding"}, "tags": ["Onboarding", "Research Lab"]}, {"item": {"url": "projects/research-lab/public/", "title": "Research Lab \u2014 Public"}, "tags": ["Research Lab", "external"]}, {"item": {"url": "projects/research-lab/public/about/", "title": "About the Research Lab"}, "tags": ["Research Lab", "external"]}, {"item": {"url": "projects/research-lab/public/how-to-engage/", "title": "Collaborate with Research Lab"}, "tags": ["Research Lab", "external"]}, {"item": {"url": "projects/research-lab/public/methodology/", "title": "Research Methodology"}, "tags": ["Research Lab", "external"]}, {"item": {"url": "projects/research-lab/reference/", "title": "Research Lab Reference"}, "tags": ["Reference", "Research Lab"]}, {"item": {"url": "projects/research-lab/roles/", "title": "Research Lab Roles"}, "tags": ["Research Lab", "Researcher"]}, {"item": {"url": "projects/research-lab/teams/", "title": "Research Lab Teams"}, "tags": ["Research Lab", "internal"]}, {"item": {"url": "projects/research-lab/workflows/", "title": "Research Lab Workflows"}, "tags": ["Process", "Research Lab"]}, {"item": {"url": "roadmap/", "title": "Roadmap"}, "tags": ["Strategy", "internal"]}, {"item": {"url": "roadmap/strategic-plan/", "title": "Strategic Plan"}, "tags": ["Strategy", "internal"]}, {"item": {"url": "team/", "title": "Team"}, "tags": ["Process", "internal"]}, {"item": {"url": "team/directory/", "title": "Directory"}, "tags": ["Reference", "internal"]}, {"item": {"url": "team/roles/", "title": "Roles"}, "tags": ["Reference", "internal"]}]}